seabom/DSBDAL_SampleProblemStatements.pdf
seabom/__init__.py
seabom/commands-hadoop.txt
seabom/01-MapReduce-LogFile/Max_Logged.java
seabom/02-MapReduce-WordCount/WordCount.java
seabom/03-MapReduce-MusicDataset-Number-of-unique-listener/Music1.java
seabom/03-MapReduce-MusicDataset-Number-of-unique-listener/TrackShared.java
seabom/04-MapReduce-MusicDataset-number-of-time-track-listen/Music2.java
seabom/04-MapReduce-MusicDataset-number-of-time-track-listen/TrackSkipped.java
seabom/05-MarReduce-MovieDataset/Movie.java
seabom/06-HBase-HiveQL-FlightInfo/Steps.txt
seabom/07-HBase-HiveQL-CustomerInfo/commands.txt
seabom/07-HBase-HiveQL-CustomerInfo/customer_info.csv
seabom/07-HBase-HiveQL-CustomerInfo/item_info.csv
seabom/07-HBase-HiveQL-CustomerInfo/order_info.csv
seabom/08-HBase-HiveQL-Online-Retail/commands.txt
seabom/08-HBase-HiveQL-Online-Retail/onlineRetail.csv
seabom/09-Python-Facebook-Metrics/Facebook.ipynb
seabom/10-Python-Iris-dataset-melting-casting-of-data/Iris-cast-melt.ipynb
seabom/11-Python-Movie-Dataset/11.ipynb
seabom/11-Python-Movie-Dataset/movie.ipynb
seabom/11-Python-Movie-Dataset/movies_metadata.csv
seabom/12-Python-Census-Bureau-Dataset/12.ipynb
seabom/12-Python-Census-Bureau-Dataset/12_Python_Census_Bureau_Dataset.ipynb
seabom/12-Python-Census-Bureau-Dataset/AdultData.csv
seabom/12-Python-Census-Bureau-Dataset/adult.csv
seabom/13-Python-Heart-Diseases/13.ipynb
seabom/14-Iris-Dataset-Model-Build-Regression-Naive-Bayes/14.ipynb
seabom/15-Python-Breast-Cancer/15.ipynb
seabom/16-Python-Census-Bureau-Model-Build-Regression-Naive-Bayes/16.ipynb
seabom/17-Visualize-Heart-Disease-Dot-Line/17.ipynb
seabom/18-Visualize-Heart-Disease-Pie-Box/18.ipynb
seabom/19-Tableau-Retail-Dataset/19.twb
seabom/20-Tableau-Retail-Dataset-Different-Param/20.twb
seabom/20-Tableau-Retail-Dataset-Different-Param/Retail-Tableau-2.twb
seabom/21-Visualize-Census-Bureau-Dot-Line/21.ipynb
seabom/22-Visualize-Census-Bureau-Pie/22.ipynb
seabom/23-Tableau-Census-Bureau/23.twb
seabom-1.0.0.dist-info/METADATA
seabom-1.0.0.dist-info/WHEEL
seabom-1.0.0.dist-info/top_level.txt
seabom-1.0.0.dist-info/RECORD
