Metadata-Version: 2.4
Name: seabom
Version: 1.0.0
Summary: Collection of DSBDA problem statements and resources
Author: Aizen
Author-email: vivekmangiraj7@gmail.com
License: MIT
Requires-Python: >=3.7
Dynamic: author
Dynamic: author-email
Dynamic: license
Dynamic: requires-python
Dynamic: summary
